{
        "response": [
                {
                        "maintainer": "Dhinesh (cool585)",
                        "oem": "Google",
                        "device": "Pixel 3XL",
                        "filename": "crDroidAndroid-13.0-20230814-crosshatch-v9.8.zip",
                        "download": "https://github.com/cool585/android_vendor_crDroidOTA/releases/download/3/crDroidAndroid-13.0-20230814-crosshatch-v9.8.zip",
                        "timestamp": 1692016147,
                        "md5": "8c35ebf3c75766b16ff574278080d9b3",
                        "sha256": "156245e7189a7c1803416eb6c1c94676e6e62c95b02a9e9b6dcbe35d2f8d382f",
                        "size": 1603035365,
                        "version": "9.8",
                        "buildtype": "Monthly",
                        "forum": "https://forum.xda-developers.com/t/4539853",
                        "gapps": "",
                        "firmware": "",
                        "modem": "",
                        "bootloader": "",
                        "recovery": "https://sourceforge.net/projects/cool585/files/blueline/crosshatch/9.x/recovery",
                        "paypal": "https://paypal.me/cool585",
                        "telegram": "https://t.me/dxt_official",
                        "dt": "https://github.com/cool585/android_device_google_crosshatch",
                        "common-dt": "",
                        "kernel": "https://github.com/cool585/android_kernel_google_bluecross"
                }
        ]
}
